code_aster/__init__.py
code_aster/command_line.py
code_aster_win-0.0.6.dist-info/LICENSE
code_aster_win-0.0.6.dist-info/METADATA
code_aster_win-0.0.6.dist-info/WHEEL
code_aster_win-0.0.6.dist-info/entry_points.txt
code_aster_win-0.0.6.dist-info/top_level.txt
code_aster_win-0.0.6.dist-info/RECORD
