Metadata-Version: 2.1
Name: code-aster-win
Version: 0.0.6
Summary: Installs code_aster and makes it easy accessible via python and shell/cmd
Home-page: UNKNOWN
Author: Daniel Steinegger
Author-email: steinegger.daniel@gmail.com
License: UNKNOWN
Platform: UNKNOWN
Classifier: Programming Language :: Python :: 3
Classifier: License :: OSI Approved :: MIT License
Classifier: Operating System :: Microsoft :: Windows
Requires-Python: >=3.6
Requires-Dist: pathlib
